wotclientdetection/__init__.py
wotclientdetection/constants.py
wotclientdetection/manager.py
wotclientdetection/shared.py
wotclientdetection/entities/__init__.py
wotclientdetection/entities/client.py
wotclientdetection/entities/launcher.py
wotclientdetection-2025.8.16.2.dist-info/licenses/LICENSE.md
wotclientdetection-2025.8.16.2.dist-info/METADATA
wotclientdetection-2025.8.16.2.dist-info/WHEEL
wotclientdetection-2025.8.16.2.dist-info/top_level.txt
wotclientdetection-2025.8.16.2.dist-info/RECORD
