Metadata-Version: 2.4
Name: wotclientdetection
Version: 2025.8.16.2
Summary: Programatically detect and delegate WoT/MT launchers and clients
Author: OpenWG.Utils Contributors
Author-email: Paul Ekshmidt <contact@kurzdor.me>
Maintainer-email: Paul Ekshmidt <contact@kurzdor.me>
License-Expression: MIT
Project-URL: Homepage, https://github.com/kurzdor/wot.clientdetection
Project-URL: Bug Reports, https://github.com/kurzdor/wot.clientdetection/issues
Project-URL: Source, https://github.com/kurzdor/wot.clientdetection
Keywords: wot,mt,launcher,client,detection
Classifier: Development Status :: 5 - Production/Stable
Classifier: Topic :: Software Development :: Build Tools
Classifier: Programming Language :: Python :: 3
Classifier: Programming Language :: Python :: 3 :: Only
Classifier: Operating System :: Microsoft :: Windows
Requires-Python: >=3
License-File: LICENSE.md
Requires-Dist: psutil
Requires-Dist: packaging
Dynamic: license-file
